{
    "user": {
        "userId": "2030",
        "username": "Commons.T"
    },
    "rank": {
        "rankShort": "SPC",
        "rankFull": "Specialist",
        "rankImageUrl": "https://7cav.us/data/roster_ranks/0/20.jpg?1741376814",
        "rankId": "20"
    },
    "realName": "Tyler Commons",
    "uniformUrl": "https://7cav.us/data/roster_uniforms/1/1160.jpg",
    "roster": "ROSTER_TYPE_PAST_MEMBERS",
    "primary": {
        "positionTitle": "Discharged",
        "positionId": "528"
    },
    "secondaries": [],
    "records": [
        {
            "recordDetails": "Enlisted in the 7th Cavalry Regiment, Assigned Boot Camp",
            "recordType": "RECORD_TYPE_TRANSFER",
            "recordDate": "2021-11-07",
            "recordUid": "45049"
        },
        {
            "recordDetails": "Transferred and Assigned Armor Crewman C/2/A/2-7",
            "recordType": "RECORD_TYPE_TRANSFER",
            "recordDate": "2021-11-12",
            "recordUid": "45312"
        },
        {
            "recordDetails": "Transferred and Assigned Armor Crewman A/2/A/2-7",
            "recordType": "RECORD_TYPE_TRANSFER",
            "recordDate": "2021-11-14",
            "recordUid": "45410"
        },
        {
            "recordDetails": "Graduated Boot Camp, Promoted to Private (E-2)",
            "recordType": "RECORD_TYPE_GRADUATION",
            "recordDate": "2021-11-15",
            "recordUid": "45533"
        },
        {
            "recordDetails": "Completed 1st Combat Mission (Operation Liberty Road (Alpha Company FTX))",
            "recordType": "RECORD_TYPE_OPERATION",
            "recordDate": "2021-11-21",
            "recordUid": "46403"
        },
        {
            "recordDetails": "Completed 2nd Combat Mission (Campaign Let Loose Tuesdays DEC21. Operation Trenched'n Tuesdays 07DEC21)",
            "recordType": "RECORD_TYPE_OPERATION",
            "recordDate": "2021-12-07",
            "recordUid": "47561"
        },
        {
            "recordDetails": "Promoted to Private First Class (E-3)",
            "recordType": "RECORD_TYPE_PROMOTION",
            "recordDate": "2021-12-14",
            "recordUid": "48024"
        },
        {
            "recordDetails": "Placed one ELOA",
            "recordType": "RECORD_TYPE_ELOA",
            "recordDate": "2022-01-13",
            "recordUid": "48191"
        },
        {
            "recordDetails": "Returned from ELOA, Transferred and Assigned Armor Crewman A/2/A/2-7",
            "recordType": "RECORD_TYPE_ELOA",
            "recordDate": "2022-02-08",
            "recordUid": "49465"
        },
        {
            "recordDetails": "Promoted to Specialist (E-4)",
            "recordType": "RECORD_TYPE_PROMOTION",
            "recordDate": "2022-02-13",
            "recordUid": "50111"
        },
        {
            "recordDetails": "AWOL Discharge, Eligible for Re-enlistment",
            "recordType": "RECORD_TYPE_DISCHARGE",
            "recordDate": "2022-03-25",
            "recordUid": "52096"
        }
    ],
    "awards": [
        {
            "awardDetails": "",
            "awardName": "Army Service Ribbon",
            "awardDate": "2021-11-15",
            "awardImageUrl": "https://7cav.us/data/roster_awards/0/40.jpg?1612676488",
            "awardUid": "23503"
        },
        {
            "awardDetails": "Awarded for the completion of one or more of the weapons qualification courses with average scores.",
            "awardName": "Grenade Marksman",
            "awardDate": "2021-11-15",
            "awardImageUrl": "https://7cav.us/data/roster_awards/0/103.jpg?1612850295",
            "awardUid": "23511"
        },
        {
            "awardDetails": "Awarded for the completion of one or more of the weapons qualification courses with above average scores.",
            "awardName": "Rifle Sharpshooter",
            "awardDate": "2021-11-15",
            "awardImageUrl": "https://7cav.us/data/roster_awards/0/101.jpg?1612850250",
            "awardUid": "23514"
        },
        {
            "awardDetails": "",
            "awardName": "Army & Air Force Presidential Unit Citation",
            "awardDate": "2003-03-19",
            "awardImageUrl": "https://7cav.us/data/roster_awards/0/61.jpg?1612677152",
            "awardUid": "23518"
        },
        {
            "awardDetails": "",
            "awardName": "Army & Air Force Presidential Unit Citation",
            "awardDate": "2004-09-02",
            "awardImageUrl": "https://7cav.us/data/roster_awards/0/61.jpg?1612677152",
            "awardUid": "23523"
        },
        {
            "awardDetails": "",
            "awardName": "Army & Air Force Presidential Unit Citation",
            "awardDate": "2009-08-11",
            "awardImageUrl": "https://7cav.us/data/roster_awards/0/61.jpg?1612677152",
            "awardUid": "23528"
        },
        {
            "awardDetails": "",
            "awardName": "Army & Air Force Presidential Unit Citation",
            "awardDate": "2010-09-19",
            "awardImageUrl": "https://7cav.us/data/roster_awards/0/61.jpg?1612677152",
            "awardUid": "23533"
        },
        {
            "awardDetails": "",
            "awardName": "Army & Air Force Presidential Unit Citation",
            "awardDate": "2011-06-03",
            "awardImageUrl": "https://7cav.us/data/roster_awards/0/61.jpg?1612677152",
            "awardUid": "23538"
        },
        {
            "awardDetails": "",
            "awardName": "Army & Air Force Presidential Unit Citation",
            "awardDate": "2021-05-17",
            "awardImageUrl": "https://7cav.us/data/roster_awards/0/61.jpg?1612677152",
            "awardUid": "23543"
        },
        {
            "awardDetails": "",
            "awardName": "Expert Infantry Badge",
            "awardDate": "2021-11-20",
            "awardImageUrl": "https://7cav.us/data/roster_awards/0/67.jpg?1673394869",
            "awardUid": "27761"
        }
    ],
    "joinDate": "2021-11-07",
    "promotionDate": "2022-02-13",
    "keycloakId": "6965827d-5e99-4da1-88f5-0a65462d374e",
    "discordId": "",
    "lastForumPostDate": "2022-02-27 21:37:39"
}