{
    "user": {
        "userId": "491",
        "username": "Marcus.J"
    },
    "rank": {
        "rankShort": "CPL",
        "rankFull": "Corporal",
        "rankImageUrl": "https://7cav.us/data/roster_ranks/0/19.jpg?1741376805",
        "rankId": "19"
    },
    "realName": "Jesser Marcus",
    "uniformUrl": "https://7cav.us/data/roster_uniforms/0/273.jpg",
    "roster": "ROSTER_TYPE_COMBAT",
    "primary": {
        "positionTitle": "Trooper 3/2/C/1-7",
        "positionId": "313"
    },
    "secondaries": [],
    "records": [
        {
            "recordDetails": "Attended the Server Administration Course",
            "recordType": "RECORD_TYPE_GRADUATION",
            "recordDate": "2021-02-20",
            "recordUid": "7585"
        },
        {
            "recordDetails": "Completed 77th Combat Mission (Operation Artificial Insolence)",
            "recordType": "RECORD_TYPE_OPERATION",
            "recordDate": "2020-12-12",
            "recordUid": "12340"
        },
        {
            "recordDetails": "Completed 76th Combat Mission (Operation Pride of Charlie, Fall 2020)",
            "recordType": "RECORD_TYPE_OPERATION",
            "recordDate": "2020-09-28",
            "recordUid": "12341"
        },
        {
            "recordDetails": "Completed 75th Combat Mission (Campaign RC East. Operation Strike Eagle)",
            "recordType": "RECORD_TYPE_OPERATION",
            "recordDate": "2020-09-27",
            "recordUid": "12342"
        },
        {
            "recordDetails": "Completed 74th Combat Mission (Operation Broken Arrow Redux)",
            "recordType": "RECORD_TYPE_OPERATION",
            "recordDate": "2020-09-14",
            "recordUid": "12343"
        },
        {
            "recordDetails": "Completed 73rd Combat Mission (Operation Starfall)",
            "recordType": "RECORD_TYPE_OPERATION",
            "recordDate": "2020-08-31",
            "recordUid": "12344"
        },
        {
            "recordDetails": "Completed 72nd Combat Mission (Campaign Winter Reprisal. Operation Chopstick)",
            "recordType": "RECORD_TYPE_OPERATION",
            "recordDate": "2020-08-30",
            "recordUid": "12345"
        },
        {
            "recordDetails": "Completed 71st Combat Mission (Operation Canyon Run)",
            "recordType": "RECORD_TYPE_OPERATION",
            "recordDate": "2020-08-09",
            "recordUid": "12346"
        },
        {
            "recordDetails": "Completed 70th Combat Mission (Operation Tonga)",
            "recordType": "RECORD_TYPE_OPERATION",
            "recordDate": "2020-08-01",
            "recordUid": "12347"
        },
        {
            "recordDetails": "Completed 69th Combat Mission (Operation Determination)",
            "recordType": "RECORD_TYPE_OPERATION",
            "recordDate": "2020-07-27",
            "recordUid": "12348"
        },
        {
            "recordDetails": "Completed 68th Combat Mission (Operation Peninsular Overture)",
            "recordType": "RECORD_TYPE_OPERATION",
            "recordDate": "2020-07-19",
            "recordUid": "12349"
        },
        {
            "recordDetails": "Completed 67th Combat Mission (Operation Tailspin)",
            "recordType": "RECORD_TYPE_OPERATION",
            "recordDate": "2020-06-29",
            "recordUid": "12350"
        },
        {
            "recordDetails": "Completed 66th Combat Mission (Campaign Boiler Plate. Operation Striker Charlie)",
            "recordType": "RECORD_TYPE_OPERATION",
            "recordDate": "2020-06-14",
            "recordUid": "12351"
        },
        {
            "recordDetails": "Completed 65th Combat Mission (Operation Steel Cloud)",
            "recordType": "RECORD_TYPE_OPERATION",
            "recordDate": "2020-05-31",
            "recordUid": "12352"
        },
        {
            "recordDetails": "Completed 64th Combat Mission (Operation Urban Anvil)",
            "recordType": "RECORD_TYPE_OPERATION",
            "recordDate": "2020-05-24",
            "recordUid": "12353"
        },
        {
            "recordDetails": "Completed 63rd Combat Mission (Campaign May Warfare Wednesday. Operation Warfare Wednesday 45)",
            "recordType": "RECORD_TYPE_OPERATION",
            "recordDate": "2020-05-14",
            "recordUid": "12354"
        },
        {
            "recordDetails": "Completed 62nd Combat Mission (Campaign Black Rain. Operation Shield Bash)",
            "recordType": "RECORD_TYPE_OPERATION",
            "recordDate": "2020-05-10",
            "recordUid": "12355"
        },
        {
            "recordDetails": "Completed 61st Combat Mission (Operation Serene Grace (Assault Phase)",
            "recordType": "RECORD_TYPE_OPERATION",
            "recordDate": "2020-04-26",
            "recordUid": "12356"
        },
        {
            "recordDetails": "Completed 60th Combat Mission (Campaign April Warfare Wednesdays. Operation Warfare Wednesdays 42)",
            "recordType": "RECORD_TYPE_OPERATION",
            "recordDate": "2020-04-23",
            "recordUid": "12357"
        },
        {
            "recordDetails": "Completed 59th Combat Mission (Campaign April Warfare Wednesdays. Operation Warfare Wednesdays 41)",
            "recordType": "RECORD_TYPE_OPERATION",
            "recordDate": "2020-04-16",
            "recordUid": "12358"
        },
        {
            "recordDetails": "Completed 58th Combat Mission (Operation Operation Nosebreaker)",
            "recordType": "RECORD_TYPE_OPERATION",
            "recordDate": "2020-03-30",
            "recordUid": "12359"
        },
        {
            "recordDetails": "Completed 57th Combat Mission (Operation Power Cord)",
            "recordType": "RECORD_TYPE_OPERATION",
            "recordDate": "2020-03-22",
            "recordUid": "12360"
        },
        {
            "recordDetails": "Completed 56th Combat Mission (Operation Rhino)",
            "recordType": "RECORD_TYPE_OPERATION",
            "recordDate": "2020-03-16",
            "recordUid": "12361"
        },
        {
            "recordDetails": "Completed 55th Combat Mission (Campaign Liberty Bell Phase 2. Operation Boxshot)",
            "recordType": "RECORD_TYPE_OPERATION",
            "recordDate": "2020-03-08",
            "recordUid": "12362"
        },
        {
            "recordDetails": "Completed 54th Combat Mission (Campaign February Tactical Thursday. Operation Tactical Thursday 12)",
            "recordType": "RECORD_TYPE_OPERATION",
            "recordDate": "2020-02-29",
            "recordUid": "12363"
        },
        {
            "recordDetails": "Completed 53rd Combat Mission (Operation Burden of Proof III)",
            "recordType": "RECORD_TYPE_OPERATION",
            "recordDate": "2020-02-16",
            "recordUid": "12364"
        },
        {
            "recordDetails": "Completed 52nd Combat Mission (Campaign Forsaken Fate Phase 1. Operation Stepping Stone)",
            "recordType": "RECORD_TYPE_OPERATION",
            "recordDate": "2020-02-09",
            "recordUid": "12365"
        },
        {
            "recordDetails": "Completed 51st Combat Mission (Campaign Let Loose Tuesdays FEB20. Operation Trenched N Tuesdays 04FEB20)",
            "recordType": "RECORD_TYPE_OPERATION",
            "recordDate": "2020-02-05",
            "recordUid": "12366"
        },
        {
            "recordDetails": "Reinstated, Reduction in Rank to Specialist (E-4), Transferred and Assigned Airborne Infantryman C/2/C/1-7",
            "recordType": "RECORD_TYPE_TRANSFER",
            "recordDate": "2020-01-27",
            "recordUid": "12367"
        },
        {
            "recordDetails": "Honorable Discharge, Eligible for Re-enlistment",
            "recordType": "RECORD_TYPE_DISCHARGE",
            "recordDate": "2019-09-19",
            "recordUid": "12368"
        },
        {
            "recordDetails": "Placed on ELOA",
            "recordType": "RECORD_TYPE_ELOA",
            "recordDate": "2019-07-03",
            "recordUid": "12369"
        },
        {
            "recordDetails": "Completed 50th Combat Mission (Campaign Green Pastures, Operation Green Pastures Phase 1)",
            "recordType": "RECORD_TYPE_OPERATION",
            "recordDate": "2019-04-29",
            "recordUid": "12370"
        },
        {
            "recordDetails": "Completed 49th Combat Mission (Campaign Shattered Hourglass, Operation Thunderclap)",
            "recordType": "RECORD_TYPE_OPERATION",
            "recordDate": "2019-04-21",
            "recordUid": "12371"
        },
        {
            "recordDetails": "Completed 48th Combat Mission (Operation Broken Camouflage)",
            "recordType": "RECORD_TYPE_OPERATION",
            "recordDate": "2019-03-31",
            "recordUid": "12372"
        },
        {
            "recordDetails": "Graduated ARMA3 Infantry Heavy Weapons Course, Class 009/03/19",
            "recordType": "RECORD_TYPE_GRADUATION",
            "recordDate": "2019-03-04",
            "recordUid": "12373"
        },
        {
            "recordDetails": "Completed 47th Combat Mission (Campaign Jungle Gauntlet, Operation Longbow)",
            "recordType": "RECORD_TYPE_OPERATION",
            "recordDate": "2019-03-03",
            "recordUid": "12374"
        },
        {
            "recordDetails": "Completed 46th Combat Mission (Campaign Hurricane Rathalos, Operation Crystal Valley)",
            "recordType": "RECORD_TYPE_OPERATION",
            "recordDate": "2019-01-06",
            "recordUid": "12375"
        },
        {
            "recordDetails": "Completed 45th Combat Mission (Campaign Jump to Leskovets Marathon, Operation Jump to Leskovets - Phase IV)",
            "recordType": "RECORD_TYPE_OPERATION",
            "recordDate": "2018-12-30",
            "recordUid": "12376"
        },
        {
            "recordDetails": "Completed 44th Combat Mission (Campaign Jump to Leskovets Marathon, Operation Jump to Leskovets - Phase III)",
            "recordType": "RECORD_TYPE_OPERATION",
            "recordDate": "2018-12-30",
            "recordUid": "12377"
        },
        {
            "recordDetails": "Completed 43rd Combat Mission (Campaign Jump to Leskovets Marathon, Operation Jump to Leskovets - Phase II)",
            "recordType": "RECORD_TYPE_OPERATION",
            "recordDate": "2018-12-30",
            "recordUid": "12378"
        },
        {
            "recordDetails": "Completed 42nd Combat Mission (Campaign Jump to Leskovets Marathon, Operation Jump to Leskovets - Phase I), Completed 5th Combat Jump",
            "recordType": "RECORD_TYPE_OPERATION",
            "recordDate": "2018-12-29",
            "recordUid": "12379"
        },
        {
            "recordDetails": "Completed 41st Combat Mission (Operation Nightfall), Completed 4th Combat Jump",
            "recordType": "RECORD_TYPE_OPERATION",
            "recordDate": "2018-12-19",
            "recordUid": "12380"
        },
        {
            "recordDetails": "Completed 40th Combat Mission (Campaign Jump To Leskovets, Operation Jump To Leskovets - Phase 1), Completed 3rd Combat Jump",
            "recordType": "RECORD_TYPE_OPERATION",
            "recordDate": "2018-12-03",
            "recordUid": "12381"
        },
        {
            "recordDetails": "Completed 39th Combat Mission (Campaign Hurricane Rathalos, Operation Redline)",
            "recordType": "RECORD_TYPE_OPERATION",
            "recordDate": "2018-11-25",
            "recordUid": "12382"
        },
        {
            "recordDetails": "Completed 38th Combat Mission (Operation Redemption)",
            "recordType": "RECORD_TYPE_OPERATION",
            "recordDate": "2018-11-10",
            "recordUid": "12383"
        },
        {
            "recordDetails": "Completed 37th Combat Mission (Operation Deluge)",
            "recordType": "RECORD_TYPE_OPERATION",
            "recordDate": "2018-11-06",
            "recordUid": "12384"
        },
        {
            "recordDetails": "Completed 36th Combat Mission (Operation Blue Support Part 2)",
            "recordType": "RECORD_TYPE_OPERATION",
            "recordDate": "2018-10-29",
            "recordUid": "12385"
        },
        {
            "recordDetails": "Completed 35th Combat Mission (Operation Linebacker)",
            "recordType": "RECORD_TYPE_OPERATION",
            "recordDate": "2018-10-22",
            "recordUid": "12386"
        },
        {
            "recordDetails": "Completed 34th Combat Mission (Operation Resolution)",
            "recordType": "RECORD_TYPE_OPERATION",
            "recordDate": "2018-10-20",
            "recordUid": "12387"
        },
        {
            "recordDetails": "Completed 33rd Combat Mission (Operation Parting Gift)",
            "recordType": "RECORD_TYPE_OPERATION",
            "recordDate": "2018-10-14",
            "recordUid": "12388"
        },
        {
            "recordDetails": "Completed 32nd Combat Mission (Operation Chimera Thief)",
            "recordType": "RECORD_TYPE_OPERATION",
            "recordDate": "2018-10-10",
            "recordUid": "12389"
        },
        {
            "recordDetails": "Completed 31st Combat Mission (Operation Jialong)",
            "recordType": "RECORD_TYPE_OPERATION",
            "recordDate": "2018-09-16",
            "recordUid": "12390"
        },
        {
            "recordDetails": "Completed 30th Combat Mission (Operation Blue Support)",
            "recordType": "RECORD_TYPE_OPERATION",
            "recordDate": "2018-09-10",
            "recordUid": "12391"
        },
        {
            "recordDetails": "Completed 29th Combat Mission (Operation Seven steeds)",
            "recordType": "RECORD_TYPE_OPERATION",
            "recordDate": "2018-09-02",
            "recordUid": "12392"
        },
        {
            "recordDetails": "Graduated ARMA3 Combat Medic Course, Class 032/08/18",
            "recordType": "RECORD_TYPE_GRADUATION",
            "recordDate": "2018-08-12",
            "recordUid": "12393"
        },
        {
            "recordDetails": "Completed 28th Combat Mission (Campaign Brass Pillar, Operation Jade Crystal)",
            "recordType": "RECORD_TYPE_OPERATION",
            "recordDate": "2018-08-12",
            "recordUid": "12394"
        },
        {
            "recordDetails": "Completed 27th Combat Mission (Campaign War Games, Operation Chapter 4)",
            "recordType": "RECORD_TYPE_OPERATION",
            "recordDate": "2018-07-28",
            "recordUid": "12395"
        },
        {
            "recordDetails": "Promoted to Corporal (E-4)",
            "recordType": "RECORD_TYPE_PROMOTION",
            "recordDate": "2018-07-16",
            "recordUid": "12396"
        },
        {
            "recordDetails": "Completed 26th Combat Mission (Operation Gipsy Blitz Redux)",
            "recordType": "RECORD_TYPE_OPERATION",
            "recordDate": "2018-07-16",
            "recordUid": "12397"
        },
        {
            "recordDetails": "Completed 25th Combat Mission (Campaign War Games, Operation Chapter 3)",
            "recordType": "RECORD_TYPE_OPERATION",
            "recordDate": "2018-07-15",
            "recordUid": "12398"
        },
        {
            "recordDetails": "Graduated NCOA Warrior Leadership Course, Class 06*06-18",
            "recordType": "RECORD_TYPE_GRADUATION",
            "recordDate": "2018-07-08",
            "recordUid": "12399"
        },
        {
            "recordDetails": "Completed 24th Combat Mission (Campaign Brass Pillar, Operation Amethyst Brandy)",
            "recordType": "RECORD_TYPE_OPERATION",
            "recordDate": "2018-07-08",
            "recordUid": "12400"
        },
        {
            "recordDetails": "Completed 23rd Combat Mission (Campaign TNG, Operation Contagion)",
            "recordType": "RECORD_TYPE_OPERATION",
            "recordDate": "2018-07-07",
            "recordUid": "12401"
        },
        {
            "recordDetails": "Completed 22nd Combat Mission (Operation Overshadow)",
            "recordType": "RECORD_TYPE_OPERATION",
            "recordDate": "2018-07-02",
            "recordUid": "12402"
        },
        {
            "recordDetails": "Graduated ARMA3 Basic Air Assault Course, Class 026/06/18",
            "recordType": "RECORD_TYPE_GRADUATION",
            "recordDate": "2018-07-01",
            "recordUid": "12403"
        },
        {
            "recordDetails": "Completed 21st Combat Mission (Campaign TNG, Operation Neutral Zone)",
            "recordType": "RECORD_TYPE_OPERATION",
            "recordDate": "2018-06-30",
            "recordUid": "12404"
        },
        {
            "recordDetails": "Completed 20th Combat Mission (Operation Gipsy Blitz)",
            "recordType": "RECORD_TYPE_OPERATION",
            "recordDate": "2018-06-24",
            "recordUid": "12405"
        },
        {
            "recordDetails": "Completed 19th Combat Mission (Operation Wooden Horse Redux)",
            "recordType": "RECORD_TYPE_OPERATION",
            "recordDate": "2018-06-23",
            "recordUid": "12406"
        },
        {
            "recordDetails": "Completed 18th Combat Mission (Operation Low Speed), Completed 2nd Combat Jump",
            "recordType": "RECORD_TYPE_OPERATION",
            "recordDate": "2018-06-04",
            "recordUid": "12407"
        },
        {
            "recordDetails": "Graduated ARMA3 Advanced Individual Training Course, Class 022/06/18",
            "recordType": "RECORD_TYPE_GRADUATION",
            "recordDate": "2018-06-03",
            "recordUid": "12408"
        },
        {
            "recordDetails": "Completed 17th Combat Mission (Operation Long Night), Completed 1st Combat Jump",
            "recordType": "RECORD_TYPE_OPERATION",
            "recordDate": "2018-06-03",
            "recordUid": "12409"
        },
        {
            "recordDetails": "Completed 16th Combat Mission (Campaign Juniper Spear Phase 2, Operation Python Strangle)",
            "recordType": "RECORD_TYPE_OPERATION",
            "recordDate": "2018-05-27",
            "recordUid": "12410"
        },
        {
            "recordDetails": "Graduated ARMA3 Indirect Fire Infantryman Course, Class 021/05/18",
            "recordType": "RECORD_TYPE_GRADUATION",
            "recordDate": "2018-05-26",
            "recordUid": "12411"
        },
        {
            "recordDetails": "Completed 15th Combat Mission (Operation Outlaw Posse)",
            "recordType": "RECORD_TYPE_OPERATION",
            "recordDate": "2018-05-20",
            "recordUid": "12412"
        },
        {
            "recordDetails": "Graduated ARMA3 Basic Mechanized Infantry Course, Class 020/05/18",
            "recordType": "RECORD_TYPE_GRADUATION",
            "recordDate": "2018-05-14",
            "recordUid": "12413"
        },
        {
            "recordDetails": "Completed 14th Combat Mission (Campaign Juniper Spear Phase 2, Operation Rhino Rush)",
            "recordType": "RECORD_TYPE_OPERATION",
            "recordDate": "2018-05-06",
            "recordUid": "12414"
        },
        {
            "recordDetails": "Completed 13th Combat Mission (Operation Lightning Dagger)",
            "recordType": "RECORD_TYPE_OPERATION",
            "recordDate": "2018-04-23",
            "recordUid": "12415"
        },
        {
            "recordDetails": "Graduated ARMA3 Basic Armor Crewman Course, Class 016/04/18",
            "recordType": "RECORD_TYPE_GRADUATION",
            "recordDate": "2018-04-22",
            "recordUid": "12416"
        },
        {
            "recordDetails": "Completed 12th Combat Mission (Campaign Juniper Spear Phase 2, Operation Crater Cover)",
            "recordType": "RECORD_TYPE_OPERATION",
            "recordDate": "2018-04-22",
            "recordUid": "12417"
        },
        {
            "recordDetails": "Graduated ARMA3 Infantry Heavy Weapons Course, Class 015/04/18",
            "recordType": "RECORD_TYPE_GRADUATION",
            "recordDate": "2018-04-15",
            "recordUid": "12418"
        },
        {
            "recordDetails": "Graduated ARMA3 Combat Lifesaver Course, Class 015/04/18",
            "recordType": "RECORD_TYPE_GRADUATION",
            "recordDate": "2018-04-10",
            "recordUid": "12419"
        },
        {
            "recordDetails": "Completed 11th Combat Mission (Campaign Juniper Spear Phase 2, Operation Indignant Hail)",
            "recordType": "RECORD_TYPE_OPERATION",
            "recordDate": "2018-04-08",
            "recordUid": "12420"
        },
        {
            "recordDetails": "Completed 10th Combat Mission (Operation Lucky Pluck)",
            "recordType": "RECORD_TYPE_OPERATION",
            "recordDate": "2018-04-02",
            "recordUid": "12421"
        },
        {
            "recordDetails": "Graduated ARMA3 Basic Radio Communication Course, Class 013/03/18",
            "recordType": "RECORD_TYPE_GRADUATION",
            "recordDate": "2018-04-01",
            "recordUid": "12422"
        },
        {
            "recordDetails": "Graduated ARMA3 Aviation Ground School, Class 013/03/18",
            "recordType": "RECORD_TYPE_GRADUATION",
            "recordDate": "2018-03-30",
            "recordUid": "12423"
        },
        {
            "recordDetails": "Graduated ARMA3 Aviation Basic Rotary Flight Course, Class 013/03/18",
            "recordType": "RECORD_TYPE_GRADUATION",
            "recordDate": "2018-03-30",
            "recordUid": "12424"
        },
        {
            "recordDetails": "Promoted to Specialist (E-4)",
            "recordType": "RECORD_TYPE_PROMOTION",
            "recordDate": "2018-03-18",
            "recordUid": "12425"
        },
        {
            "recordDetails": "Completed 9th Combat Mission (Campaign Juniper Spear, Operation Window Shopping)",
            "recordType": "RECORD_TYPE_OPERATION",
            "recordDate": "2018-03-11",
            "recordUid": "12426"
        },
        {
            "recordDetails": "Completed 8th Combat Mission (Operation Blind Salvation)",
            "recordType": "RECORD_TYPE_OPERATION",
            "recordDate": "2018-03-10",
            "recordUid": "12427"
        },
        {
            "recordDetails": "Completed 7th Combat Mission (Campaign Juniper Spear, Operation Hearts and Minds)",
            "recordType": "RECORD_TYPE_OPERATION",
            "recordDate": "2018-03-06",
            "recordUid": "12428"
        },
        {
            "recordDetails": "Completed 6th Combat Mission (Operation Palm Crescent)",
            "recordType": "RECORD_TYPE_OPERATION",
            "recordDate": "2018-02-26",
            "recordUid": "12429"
        },
        {
            "recordDetails": "Completed 5th Combat Mission (Campaign Juniper Spear, Operation Thunder and Lightning)",
            "recordType": "RECORD_TYPE_OPERATION",
            "recordDate": "2018-02-25",
            "recordUid": "12430"
        },
        {
            "recordDetails": "Graduated ARMA3 Basic Individual Training Course, Class 008/02/18",
            "recordType": "RECORD_TYPE_GRADUATION",
            "recordDate": "2018-02-25",
            "recordUid": "12431"
        },
        {
            "recordDetails": "Completed 4th Combat Mission (Campaign Juniper Spear, Operation Dealbreaker)",
            "recordType": "RECORD_TYPE_OPERATION",
            "recordDate": "2018-02-11",
            "recordUid": "12432"
        },
        {
            "recordDetails": "Completed 3rd Combat Mission (Campaign War for Catachan, Operation Napalm Breakfast)",
            "recordType": "RECORD_TYPE_OPERATION",
            "recordDate": "2018-02-10",
            "recordUid": "12433"
        },
        {
            "recordDetails": "Graduated ARMA3 Basic Land Navigation Course, Class 005/02/18",
            "recordType": "RECORD_TYPE_GRADUATION",
            "recordDate": "2018-02-04",
            "recordUid": "12434"
        },
        {
            "recordDetails": "Completed 2nd Combat Mission (Operation High Ball)",
            "recordType": "RECORD_TYPE_OPERATION",
            "recordDate": "2018-02-04",
            "recordUid": "12435"
        },
        {
            "recordDetails": "Graduated ARMA3 Basic Airborne Course, Class 003/01/18",
            "recordType": "RECORD_TYPE_GRADUATION",
            "recordDate": "2018-01-21",
            "recordUid": "12436"
        },
        {
            "recordDetails": "Promoted to Private First Class (E-3)",
            "recordType": "RECORD_TYPE_PROMOTION",
            "recordDate": "2018-01-17",
            "recordUid": "12437"
        },
        {
            "recordDetails": "Transferred and Assigned Airborne Infantryman B/2/C/1-7",
            "recordType": "RECORD_TYPE_TRANSFER",
            "recordDate": "2018-01-17",
            "recordUid": "12438"
        },
        {
            "recordDetails": "Graduated Boot Camp, Promoted to Private (E-2)",
            "recordType": "RECORD_TYPE_GRADUATION",
            "recordDate": "2017-12-18",
            "recordUid": "12439"
        },
        {
            "recordDetails": "Completed 1st Combat Mission (Campaign Volsunga, Operation Andvaranaut)",
            "recordType": "RECORD_TYPE_OPERATION",
            "recordDate": "2017-12-18",
            "recordUid": "12440"
        },
        {
            "recordDetails": "Enlisted in the 7th Cavalry Regiment, Assigned Boot Camp 049/12/17",
            "recordType": "RECORD_TYPE_TRANSFER",
            "recordDate": "2017-12-07",
            "recordUid": "12441"
        },
        {
            "recordDetails": "Completed 78th Combat Mission (Campaign RC East. Operation COP Carter)",
            "recordType": "RECORD_TYPE_OPERATION",
            "recordDate": "2021-01-24",
            "recordUid": "13009"
        },
        {
            "recordDetails": "Completed 79th Combat Mission (Operation Rocky Start)",
            "recordType": "RECORD_TYPE_OPERATION",
            "recordDate": "2021-02-13",
            "recordUid": "14728"
        },
        {
            "recordDetails": "Completed 80th Combat Mission (Campaign Panjshir V. Operation Mauze)",
            "recordType": "RECORD_TYPE_OPERATION",
            "recordDate": "2021-02-20",
            "recordUid": "15983"
        },
        {
            "recordDetails": "Completed 81st Combat Mission (Campaign Paper Trail. Operation Purple Warrior)",
            "recordType": "RECORD_TYPE_OPERATION",
            "recordDate": "2021-02-27",
            "recordUid": "16602"
        },
        {
            "recordDetails": "Completed 82nd Combat Mission (Operation Northern Lights, Phase I)",
            "recordType": "RECORD_TYPE_OPERATION",
            "recordDate": "2021-03-06",
            "recordUid": "17178"
        },
        {
            "recordDetails": "Completed 83rd Combat Mission (Operation Northern Lights, Phase II)",
            "recordType": "RECORD_TYPE_OPERATION",
            "recordDate": "2021-03-07",
            "recordUid": "17201"
        },
        {
            "recordDetails": "Completed 84th Combat Mission (Campaign Northern Lights. Operation Northern Lights, Phase III)",
            "recordType": "RECORD_TYPE_OPERATION",
            "recordDate": "2021-03-13",
            "recordUid": "17367"
        },
        {
            "recordDetails": "Promoted to Corporal (E-4)",
            "recordType": "RECORD_TYPE_PROMOTION",
            "recordDate": "2021-02-19",
            "recordUid": "17407"
        },
        {
            "recordDetails": "Completed 85th Combat Mission (Campaign March Warfare Wednesday 2021. Operation Warfare Wednesday 85)",
            "recordType": "RECORD_TYPE_OPERATION",
            "recordDate": "2021-03-17",
            "recordUid": "18118"
        },
        {
            "recordDetails": "Completed 86th Combat Mission (Operation Northern Lights, Phase V)",
            "recordType": "RECORD_TYPE_OPERATION",
            "recordDate": "2021-03-20",
            "recordUid": "18422"
        },
        {
            "recordDetails": "Completed 87th Combat Mission (Operation Northern Lights, Phase VI)",
            "recordType": "RECORD_TYPE_OPERATION",
            "recordDate": "2021-03-23",
            "recordUid": "20921"
        },
        {
            "recordDetails": "Completed 88th Combat Mission (Operation Northern Lights, Phase VII)",
            "recordType": "RECORD_TYPE_OPERATION",
            "recordDate": "2021-03-27",
            "recordUid": "24808"
        },
        {
            "recordDetails": "Completed 89th Combat Mission (Operation Northern Lights, Phase VIII)",
            "recordType": "RECORD_TYPE_OPERATION",
            "recordDate": "2021-03-28",
            "recordUid": "24849"
        },
        {
            "recordDetails": "Completed 90th Combat Mission (Operation Northern Lights, Phase IX)",
            "recordType": "RECORD_TYPE_OPERATION",
            "recordDate": "2021-04-02",
            "recordUid": "26840"
        },
        {
            "recordDetails": "Completed 91st Combat Mission (Operation Prairie Fire)",
            "recordType": "RECORD_TYPE_OPERATION",
            "recordDate": "2021-05-08",
            "recordUid": "35393"
        },
        {
            "recordDetails": "Completed 92nd Combat Mission (Operation Sand Pounders)",
            "recordType": "RECORD_TYPE_OPERATION",
            "recordDate": "2021-05-22",
            "recordUid": "36280"
        },
        {
            "recordDetails": "Completed 93rd Combat Mission (Operation Landslide)",
            "recordType": "RECORD_TYPE_OPERATION",
            "recordDate": "2021-05-23",
            "recordUid": "36438"
        },
        {
            "recordDetails": "Completed 94th Combat Mission (Operation Platinum Fox)",
            "recordType": "RECORD_TYPE_OPERATION",
            "recordDate": "2021-06-05",
            "recordUid": "36878"
        },
        {
            "recordDetails": "Completed 95th Combat Mission (Campaign 17th Parallel. Operation Junction City)",
            "recordType": "RECORD_TYPE_OPERATION",
            "recordDate": "2021-06-26",
            "recordUid": "37919"
        },
        {
            "recordDetails": "Completed 96th Combat Mission (Operation Driven Star)",
            "recordType": "RECORD_TYPE_OPERATION",
            "recordDate": "2021-07-03",
            "recordUid": "38202"
        },
        {
            "recordDetails": "Completed 97th Combat Mission (Campaign 17th Parallel. Operation Hue)",
            "recordType": "RECORD_TYPE_OPERATION",
            "recordDate": "2021-07-24",
            "recordUid": "39707"
        },
        {
            "recordDetails": "Completed 98th Combat Mission (Operation World Cup)",
            "recordType": "RECORD_TYPE_OPERATION",
            "recordDate": "2021-08-07",
            "recordUid": "40512"
        },
        {
            "recordDetails": "Completed 99th Combat Mission (Operation Burning Eagle)",
            "recordType": "RECORD_TYPE_OPERATION",
            "recordDate": "2021-08-21",
            "recordUid": "41119"
        },
        {
            "recordDetails": "Completed 100th Combat Mission (Operation Guardian Angel)",
            "recordType": "RECORD_TYPE_OPERATION",
            "recordDate": "2021-09-05",
            "recordUid": "41887"
        },
        {
            "recordDetails": "Completed 101st Combat Mission (Campaign Slaughter Sunday's. Operation Slaughter Sunday's 31OCT21)",
            "recordType": "RECORD_TYPE_OPERATION",
            "recordDate": "2021-10-31",
            "recordUid": "45067"
        },
        {
            "recordDetails": "Completed 102nd Combat Mission (Operation Lost Time - 24 Hour Operation)",
            "recordType": "RECORD_TYPE_OPERATION",
            "recordDate": "2021-12-12",
            "recordUid": "47667"
        },
        {
            "recordDetails": "Completed 103rd Combat Mission (Campaign Back Again. Operation Fallen Fruit)",
            "recordType": "RECORD_TYPE_OPERATION",
            "recordDate": "2022-01-08",
            "recordUid": "48209"
        },
        {
            "recordDetails": "Graduated ARMA3 Basic Airborne Course",
            "recordType": "RECORD_TYPE_GRADUATION",
            "recordDate": "2022-01-21",
            "recordUid": "48653"
        },
        {
            "recordDetails": "Completed 104th Combat Mission (Campaign January Warfare Wednesday 2022. Operation Warfare Wednesday 124)",
            "recordType": "RECORD_TYPE_OPERATION",
            "recordDate": "2022-01-12",
            "recordUid": "48673"
        },
        {
            "recordDetails": "Completed 105th Combat Mission (Operation Ardennes Offensive 1944)",
            "recordType": "RECORD_TYPE_OPERATION",
            "recordDate": "2022-01-15",
            "recordUid": "48720"
        },
        {
            "recordDetails": "Completed 106th Combat Mission (Campaign Shapur Scenarios. Operation Jaws of Death)",
            "recordType": "RECORD_TYPE_OPERATION",
            "recordDate": "2022-02-02",
            "recordUid": "49434"
        },
        {
            "recordDetails": "Completed 107th Combat Mission (Campaign Rogal Dorn. Operation Gravis)",
            "recordType": "RECORD_TYPE_OPERATION",
            "recordDate": "2022-04-10",
            "recordUid": "53862"
        },
        {
            "recordDetails": "Completed 108th Combat Mission (Campaign May Warfare Wednesday 2022. Operation Warfare Wednesday 140)",
            "recordType": "RECORD_TYPE_OPERATION",
            "recordDate": "2022-05-18",
            "recordUid": "55729"
        },
        {
            "recordDetails": "Completed 109th Combat Mission (Operation Martian Dust)",
            "recordType": "RECORD_TYPE_OPERATION",
            "recordDate": "2022-07-31",
            "recordUid": "59885"
        },
        {
            "recordDetails": "Completed 110th Combat Mission (Campaign Wild East. Operation Melt and Blow)",
            "recordType": "RECORD_TYPE_OPERATION",
            "recordDate": "2022-10-01",
            "recordUid": "64252"
        },
        {
            "recordDetails": "Completed 111th Combat Mission (Operation Sandbox - 24 Hour 2022)",
            "recordType": "RECORD_TYPE_OPERATION",
            "recordDate": "2022-12-10",
            "recordUid": "68775"
        },
        {
            "recordDetails": "Completed 112th Combat Mission (Campaign February Warfare Wednesday 2023. Operation Warfare Wednesday 176)",
            "recordType": "RECORD_TYPE_OPERATION",
            "recordDate": "2023-02-15",
            "recordUid": "71878"
        },
        {
            "recordDetails": "Completed 113th Combat Mission (Operation Iron Hammer 30APR23)",
            "recordType": "RECORD_TYPE_OPERATION",
            "recordDate": "2023-04-30",
            "recordUid": "77397"
        },
        {
            "recordDetails": "Completed 114th Combat Mission (Campaign Andean. Operation Rapid Response)",
            "recordType": "RECORD_TYPE_OPERATION",
            "recordDate": "2023-05-04",
            "recordUid": "77846"
        },
        {
            "recordDetails": "Completed 115th Combat Mission (Campaign May Warfare Wednesday 2023. Operation Warfare Wednesday 188)",
            "recordType": "RECORD_TYPE_OPERATION",
            "recordDate": "2023-05-10",
            "recordUid": "78062"
        },
        {
            "recordDetails": "Completed 116th Combat Mission (Campaign Andean. Operation Hot Blood)",
            "recordType": "RECORD_TYPE_OPERATION",
            "recordDate": "2023-05-13",
            "recordUid": "78212"
        },
        {
            "recordDetails": "Completed 117th Combat Mission (Campaign Overlord 1944 (2023). Operation Operation Neptune: H-4 (2023))",
            "recordType": "RECORD_TYPE_OPERATION",
            "recordDate": "2023-06-03",
            "recordUid": "79583"
        },
        {
            "recordDetails": "Completed 118th Combat Mission (Campaign Overlord 1944 (2023). Operation Neptune: H-Hour (2023))",
            "recordType": "RECORD_TYPE_OPERATION",
            "recordDate": "2023-06-05",
            "recordUid": "79675"
        },
        {
            "recordDetails": "Completed 119th Combat Mission (Campaign June Warfare Wednesday. Operation Warfare Wednesday 193)",
            "recordType": "RECORD_TYPE_OPERATION",
            "recordDate": "2023-06-15",
            "recordUid": "80441"
        },
        {
            "recordDetails": "Completed 120th Combat Mission (Campaign Andean. Operation Valiant Hawk)",
            "recordType": "RECORD_TYPE_OPERATION",
            "recordDate": "2023-06-18",
            "recordUid": "80487"
        },
        {
            "recordDetails": "Completed 121st Combat Mission (Campaign Andean. Operation Fever Pitch)",
            "recordType": "RECORD_TYPE_OPERATION",
            "recordDate": "2023-07-08",
            "recordUid": "81819"
        },
        {
            "recordDetails": "Completed 122nd Combat Mission (Campaign July Warfare Wednesday. Operation Warfare Wednesday 197)",
            "recordType": "RECORD_TYPE_OPERATION",
            "recordDate": "2023-07-12",
            "recordUid": "82284"
        },
        {
            "recordDetails": "Letter of Reprimand - 30 Day NFA",
            "recordType": "RECORD_TYPE_DISCIPLINARY",
            "recordDate": "2023-08-19",
            "recordUid": "83991"
        },
        {
            "recordDetails": "Completed 123rd Combat Mission (Campaign September Warfare Wednesday. Operation Warfare Wednesday 207)",
            "recordType": "RECORD_TYPE_OPERATION",
            "recordDate": "2023-09-20",
            "recordUid": "86209"
        },
        {
            "recordDetails": "Completed 124th Combat Mission (Campaign Warfare Wednesday OCT23. Operation Warfare Wednesday 212)",
            "recordType": "RECORD_TYPE_OPERATION",
            "recordDate": "2023-10-25",
            "recordUid": "88733"
        },
        {
            "recordDetails": "Completed 125th Combat Mission (Operation Lost Souls)",
            "recordType": "RECORD_TYPE_OPERATION",
            "recordDate": "2023-10-28",
            "recordUid": "89495"
        },
        {
            "recordDetails": "Completed 126th Combat Mission (Operation Sumava Freedom)",
            "recordType": "RECORD_TYPE_OPERATION",
            "recordDate": "2023-12-09",
            "recordUid": "91884"
        },
        {
            "recordDetails": "Completed 128th Combat Mission (Campaign January 2024 Warfare Wednesday. Operation Warfare Wednesday 221)",
            "recordType": "RECORD_TYPE_OPERATION",
            "recordDate": "2024-01-17",
            "recordUid": "93461"
        },
        {
            "recordDetails": "Completed 129th Combat Mission (Campaign January 2024 Warfare Wednesday. Operation Warfare Wednesday 223)",
            "recordType": "RECORD_TYPE_OPERATION",
            "recordDate": "2024-02-01",
            "recordUid": "94095"
        },
        {
            "recordDetails": "Completed 127th Combat Mission (Campaign Warfare Wednesday DEC23. Operation Warfare Wednesday 219)",
            "recordType": "RECORD_TYPE_OPERATION",
            "recordDate": "2023-12-13",
            "recordUid": "94807"
        },
        {
            "recordDetails": "Completed 130th Combat Mission (Operation Shanty)",
            "recordType": "RECORD_TYPE_OPERATION",
            "recordDate": "2024-03-09",
            "recordUid": "97004"
        },
        {
            "recordDetails": "Completed 131st Combat Mission (Campaign April 2024 WFW. Operation Warfare Wednesday 234)",
            "recordType": "RECORD_TYPE_OPERATION",
            "recordDate": "2024-04-17",
            "recordUid": "100028"
        },
        {
            "recordDetails": "Completed 132nd Combat Mission (Operation Trail Blazer)",
            "recordType": "RECORD_TYPE_OPERATION",
            "recordDate": "2024-04-27",
            "recordUid": "101026"
        },
        {
            "recordDetails": "Completed 133rd Combat Mission (Campaign June 2024 WFW. Operation Warfare Wednesday 242)",
            "recordType": "RECORD_TYPE_OPERATION",
            "recordDate": "2024-06-12",
            "recordUid": "105165"
        },
        {
            "recordDetails": "Completed 134th Combat Mission (Campaign June 2024 WFW. Operation Warfare Wednesday 244)",
            "recordType": "RECORD_TYPE_OPERATION",
            "recordDate": "2024-06-26",
            "recordUid": "105929"
        },
        {
            "recordDetails": "Completed 135th Combat Mission (Operation Three-of-a-Kind)",
            "recordType": "RECORD_TYPE_OPERATION",
            "recordDate": "2024-07-13",
            "recordUid": "107120"
        },
        {
            "recordDetails": "Completed 136th Combat Mission (Operation Snowball)",
            "recordType": "RECORD_TYPE_OPERATION",
            "recordDate": "2024-08-24",
            "recordUid": "110935"
        },
        {
            "recordDetails": "Completed 137th Combat Mission (Operation Warfare Wednesday 249)",
            "recordType": "RECORD_TYPE_OPERATION",
            "recordDate": "2024-08-28",
            "recordUid": "111736"
        },
        {
            "recordDetails": "Completed 138th Combat Mission (Operation Tasty Reduction)Completed 5th Combat Jump",
            "recordType": "RECORD_TYPE_OPERATION",
            "recordDate": "2024-10-06",
            "recordUid": "115408"
        },
        {
            "recordDetails": "Completed 139th Combat Mission (Operation Losefast Winslow)",
            "recordType": "RECORD_TYPE_OPERATION",
            "recordDate": "2024-10-13",
            "recordUid": "115942"
        },
        {
            "recordDetails": "Completed 140th Combat Mission (Operation Conquest TvT)",
            "recordType": "RECORD_TYPE_OPERATION",
            "recordDate": "2024-12-08",
            "recordUid": "119220"
        },
        {
            "recordDetails": "Completed 141st Combat Mission (Campaign Iron Horse. Operation Freedom's Canopy)",
            "recordType": "RECORD_TYPE_OPERATION",
            "recordDate": "2025-02-02",
            "recordUid": "122055"
        }
    ],
    "awards": [
        {
            "awardDetails": "Operation Purple Warrior",
            "awardName": "Army Meritorious Unit Citation",
            "awardDate": "2021-03-10",
            "awardImageUrl": "https://7cav.us/data/roster_awards/0/64.jpg?1612677213",
            "awardUid": "5568"
        },
        {
            "awardDetails": "",
            "awardName": "Army & Air Force Presidential Unit Citation",
            "awardDate": "2011-06-02",
            "awardImageUrl": "https://7cav.us/data/roster_awards/0/61.jpg?1612677152",
            "awardUid": "5895"
        },
        {
            "awardDetails": "",
            "awardName": "Army & Air Force Presidential Unit Citation",
            "awardDate": "2010-09-18",
            "awardImageUrl": "https://7cav.us/data/roster_awards/0/61.jpg?1612677152",
            "awardUid": "5896"
        },
        {
            "awardDetails": "",
            "awardName": "Army & Air Force Presidential Unit Citation",
            "awardDate": "2009-08-10",
            "awardImageUrl": "https://7cav.us/data/roster_awards/0/61.jpg?1612677152",
            "awardUid": "5897"
        },
        {
            "awardDetails": "",
            "awardName": "Army & Air Force Presidential Unit Citation",
            "awardDate": "2004-09-01",
            "awardImageUrl": "https://7cav.us/data/roster_awards/0/61.jpg?1612677152",
            "awardUid": "5898"
        },
        {
            "awardDetails": "",
            "awardName": "Army & Air Force Presidential Unit Citation",
            "awardDate": "2003-03-18",
            "awardImageUrl": "https://7cav.us/data/roster_awards/0/61.jpg?1612677152",
            "awardUid": "5899"
        },
        {
            "awardDetails": "",
            "awardName": "Combat Infantry Badge 4th Award",
            "awardDate": "2018-06-23",
            "awardImageUrl": "https://7cav.us/data/roster_awards/0/71.jpg?1612677477",
            "awardUid": "5900"
        },
        {
            "awardDetails": "Campaign Juniper Spear Phase 2 (ARMA3)",
            "awardName": "United Nations Service Medal",
            "awardDate": "2018-06-06",
            "awardImageUrl": "https://7cav.us/data/roster_awards/0/42.jpg?1612676525",
            "awardUid": "5901"
        },
        {
            "awardDetails": "",
            "awardName": "Expert Infantry Badge",
            "awardDate": "2017-12-17",
            "awardImageUrl": "https://7cav.us/data/roster_awards/0/67.jpg?1673394869",
            "awardUid": "5902"
        },
        {
            "awardDetails": "",
            "awardName": "Army Service Ribbon",
            "awardDate": "2017-12-17",
            "awardImageUrl": "https://7cav.us/data/roster_awards/0/40.jpg?1612676488",
            "awardUid": "5903"
        },
        {
            "awardDetails": "",
            "awardName": "Army Parachutist Badge",
            "awardDate": "2018-01-20",
            "awardImageUrl": "https://7cav.us/data/roster_awards/0/83.jpg?1612678149",
            "awardUid": "5904"
        },
        {
            "awardDetails": "",
            "awardName": "Combat Infantry Badge",
            "awardDate": "2018-02-24",
            "awardImageUrl": "https://7cav.us/data/roster_awards/0/68.jpg?1612677377",
            "awardUid": "5905"
        },
        {
            "awardDetails": "",
            "awardName": "Combat Infantry Badge 2nd Award",
            "awardDate": "2018-04-01",
            "awardImageUrl": "https://7cav.us/data/roster_awards/0/69.jpg?1612677441",
            "awardUid": "5906"
        },
        {
            "awardDetails": "Campaign Juniper Spear Phase 1 (ARMA3)",
            "awardName": "United Nations Service Medal",
            "awardDate": "2018-04-13",
            "awardImageUrl": "https://7cav.us/data/roster_awards/0/42.jpg?1612676525",
            "awardUid": "5907"
        },
        {
            "awardDetails": "Operation Lucky Pluck",
            "awardName": "Prisoner of War Medal",
            "awardDate": "2018-04-29",
            "awardImageUrl": "https://7cav.us/data/roster_awards/0/22.jpg?1612674621",
            "awardUid": "5908"
        },
        {
            "awardDetails": "",
            "awardName": "Combat Infantry Badge 3rd Award",
            "awardDate": "2018-05-19",
            "awardImageUrl": "https://7cav.us/data/roster_awards/0/70.jpg?1612677459",
            "awardUid": "5909"
        },
        {
            "awardDetails": "",
            "awardName": "Air Assault Badge",
            "awardDate": "2018-06-30",
            "awardImageUrl": "https://7cav.us/data/roster_awards/0/86.jpg?1612678230",
            "awardUid": "5910"
        },
        {
            "awardDetails": "Initial",
            "awardName": "Overseas Service Ribbon",
            "awardDate": "2018-07-25",
            "awardImageUrl": "https://7cav.us/data/roster_awards/0/43.jpg?1713711737",
            "awardUid": "5911"
        },
        {
            "awardDetails": "",
            "awardName": "Expert Field Medical Badge",
            "awardDate": "2018-08-11",
            "awardImageUrl": "https://7cav.us/data/roster_awards/0/72.jpg?1612677819",
            "awardUid": "5912"
        },
        {
            "awardDetails": "Operation Jade Crystal",
            "awardName": "Purple Heart",
            "awardDate": "2018-09-04",
            "awardImageUrl": "https://7cav.us/data/roster_awards/0/13.jpg?1612668156",
            "awardUid": "5913"
        },
        {
            "awardDetails": "",
            "awardName": "Army Superior Unit Citation",
            "awardDate": "2018-10-13",
            "awardImageUrl": "https://7cav.us/data/roster_awards/0/65.jpg?1612677240",
            "awardUid": "5914"
        },
        {
            "awardDetails": "Operation Parting Gift",
            "awardName": "Prisoner of War Medal",
            "awardDate": "2018-10-28",
            "awardImageUrl": "https://7cav.us/data/roster_awards/0/22.jpg?1612674621",
            "awardUid": "5915"
        },
        {
            "awardDetails": "Operation Redemption (24Hr)",
            "awardName": "Prisoner of War Medal",
            "awardDate": "2018-11-26",
            "awardImageUrl": "https://7cav.us/data/roster_awards/0/22.jpg?1612674621",
            "awardUid": "5916"
        },
        {
            "awardDetails": "",
            "awardName": "Army Good Conduct Medal",
            "awardDate": "2018-12-17",
            "awardImageUrl": "https://7cav.us/data/roster_awards/0/23.jpg?1612674641",
            "awardUid": "5917"
        },
        {
            "awardDetails": "Campaign Jump to Leskovets Marathon (ARMA3)",
            "awardName": "United Nations Service Medal",
            "awardDate": "2019-01-08",
            "awardImageUrl": "https://7cav.us/data/roster_awards/0/42.jpg?1612676525",
            "awardUid": "5918"
        },
        {
            "awardDetails": "Pride of Charlie",
            "awardName": "Army Achievement Medal",
            "awardDate": "2020-03-29",
            "awardImageUrl": "https://7cav.us/data/roster_awards/0/21.jpg?1612674596",
            "awardUid": "5919"
        },
        {
            "awardDetails": "Operation Nosebreaker",
            "awardName": "Army Meritorious Unit Citation",
            "awardDate": "2020-04-13",
            "awardImageUrl": "https://7cav.us/data/roster_awards/0/64.jpg?1612677213",
            "awardUid": "5920"
        },
        {
            "awardDetails": "1st Bronze Knot",
            "awardName": "Army Good Conduct Medal",
            "awardDate": "2020-07-12",
            "awardImageUrl": "https://7cav.us/data/roster_awards/0/23.jpg?1612674641",
            "awardUid": "5921"
        },
        {
            "awardDetails": "Operation Urban Anvil",
            "awardName": "Army Meritorious Unit Citation",
            "awardDate": "2020-07-31",
            "awardImageUrl": "https://7cav.us/data/roster_awards/0/64.jpg?1612677213",
            "awardUid": "5922"
        },
        {
            "awardDetails": "Awarded for the completion of one or more of the weapons qualification courses with excellent scores.",
            "awardName": "M-203 Expert",
            "awardDate": "2023-01-20",
            "awardImageUrl": "https://7cav.us/data/roster_awards/0/114.jpg?1612850587",
            "awardUid": "5923"
        },
        {
            "awardDetails": "Awarded for the completion of one or more of the weapons qualification courses with excellent scores.",
            "awardName": "Grenade Expert",
            "awardDate": "2020-08-03",
            "awardImageUrl": "https://7cav.us/data/roster_awards/0/105.jpg?1612850347",
            "awardUid": "5924"
        },
        {
            "awardDetails": "Awarded for the completion of one or more of the weapons qualification courses with excellent scores.",
            "awardName": "Rifle Expert",
            "awardDate": "2020-08-03",
            "awardImageUrl": "https://7cav.us/data/roster_awards/0/102.jpg?1612850272",
            "awardUid": "5925"
        },
        {
            "awardDetails": "Operation Northern Lights",
            "awardName": "United Nations Service Medal",
            "awardDate": "2021-04-12",
            "awardImageUrl": "https://7cav.us/data/roster_awards/0/42.jpg?1612676525",
            "awardUid": "12459"
        },
        {
            "awardDetails": "Operation Artificial Insolence",
            "awardName": "Prisoner of War Medal",
            "awardDate": "2021-05-06",
            "awardImageUrl": "https://7cav.us/data/roster_awards/0/22.jpg?1612674621",
            "awardUid": "16712"
        },
        {
            "awardDetails": "",
            "awardName": "Army & Air Force Presidential Unit Citation",
            "awardDate": "2021-05-16",
            "awardImageUrl": "https://7cav.us/data/roster_awards/0/61.jpg?1612677152",
            "awardUid": "17375"
        },
        {
            "awardDetails": "2nd Bronze Knot",
            "awardName": "Army Good Conduct Medal",
            "awardDate": "2021-07-13",
            "awardImageUrl": "https://7cav.us/data/roster_awards/0/23.jpg?1612674641",
            "awardUid": "20135"
        },
        {
            "awardDetails": "",
            "awardName": "Cavalry Centurion Medal",
            "awardDate": "2021-09-16",
            "awardImageUrl": "https://7cav.us/data/roster_awards/0/41.jpg?1612676506",
            "awardUid": "21677"
        },
        {
            "awardDetails": "3rd Bronze Knot",
            "awardName": "Army Good Conduct Medal",
            "awardDate": "2022-07-13",
            "awardImageUrl": "https://7cav.us/data/roster_awards/0/23.jpg?1612674641",
            "awardUid": "31740"
        },
        {
            "awardDetails": "Awarded for the completion of one or more of the weapons qualification courses with average scores.",
            "awardName": "Machine Gun Marksman",
            "awardDate": "2023-01-20",
            "awardImageUrl": "https://7cav.us/data/roster_awards/0/115.jpg?1612850619",
            "awardUid": "37009"
        },
        {
            "awardDetails": "Awarded for the completion of one or more of the weapons qualification courses with excellent scores.",
            "awardName": "Recoilless Rifle Expert",
            "awardDate": "2023-01-20",
            "awardImageUrl": "https://7cav.us/data/roster_awards/0/120.jpg?1612850723",
            "awardUid": "37010"
        },
        {
            "awardDetails": "2023 1st Battalion Recruitment Competition",
            "awardName": "Army Achievement Medal",
            "awardDate": "2023-04-09",
            "awardImageUrl": "https://7cav.us/data/roster_awards/0/21.jpg?1612674596",
            "awardUid": "40139"
        },
        {
            "awardDetails": "",
            "awardName": "D-Day Commemorative Medal",
            "awardDate": "2023-06-15",
            "awardImageUrl": "https://7cav.us/data/roster_awards/0/50.jpg?1612676791",
            "awardUid": "42582"
        },
        {
            "awardDetails": "1st Silver Knot",
            "awardName": "Army Good Conduct Medal",
            "awardDate": "2023-07-13",
            "awardImageUrl": "https://7cav.us/data/roster_awards/0/23.jpg?1612674641",
            "awardUid": "44435"
        },
        {
            "awardDetails": "50 Operation Milestone",
            "awardName": "Overseas Service Ribbon",
            "awardDate": "2023-08-20",
            "awardImageUrl": "https://7cav.us/data/roster_awards/0/43.jpg?1713711737",
            "awardUid": "45419"
        },
        {
            "awardDetails": "Campaign Andean",
            "awardName": "United Nations Service Medal",
            "awardDate": "2023-09-18",
            "awardImageUrl": "https://7cav.us/data/roster_awards/0/42.jpg?1612676525",
            "awardUid": "45780"
        },
        {
            "awardDetails": "Awarded for the completion of one or more of the weapons qualification courses with excellent scores.",
            "awardName": "Pistol Expert",
            "awardDate": "2024-02-04",
            "awardImageUrl": "https://7cav.us/data/roster_awards/0/108.jpg?1612850440",
            "awardUid": "50629"
        },
        {
            "awardDetails": "Operation Trail Blazer",
            "awardName": "Prisoner of War Medal",
            "awardDate": "2024-04-28",
            "awardImageUrl": "https://7cav.us/data/roster_awards/0/22.jpg?1612674621",
            "awardUid": "54766"
        },
        {
            "awardDetails": "100 Operation Milestone",
            "awardName": "Overseas Service Ribbon",
            "awardDate": "2024-05-06",
            "awardImageUrl": "https://7cav.us/data/roster_awards/0/43.jpg?1713711737",
            "awardUid": "55233"
        },
        {
            "awardDetails": "2nd Silver Knot",
            "awardName": "Army Good Conduct Medal",
            "awardDate": "2024-08-13",
            "awardImageUrl": "https://7cav.us/data/roster_awards/0/23.jpg?1612674641",
            "awardUid": "61666"
        }
    ],
    "joinDate": "2017-12-06",
    "promotionDate": "2021-02-19",
    "keycloakId": "b6ce7f14-4fb6-4104-82ce-3b26cb41e778",
    "discordId": "360985561399558144",
    "lastForumPostDate": "2025-03-17 01:07:28"
}