{
    "user": {
        "userId": "5655",
        "username": "Evans.J"
    },
    "rank": {
        "rankShort": "SPC",
        "rankFull": "Specialist",
        "rankImageUrl": "https://7cav.us/data/roster_ranks/0/20.jpg?1741376814",
        "rankId": "20"
    },
    "realName": "James Evans",
    "uniformUrl": "https://7cav.us/data/roster_uniforms/2/2789.jpg",
    "roster": "ROSTER_TYPE_COMBAT",
    "primary": {
        "positionTitle": "Trooper 3/2/A/2-7",
        "positionId": "372"
    },
    "secondaries": [],
    "records": [
        {
            "recordDetails": "Enlisted in the 7th Cavalry Regiment, Assigned Boot Camp",
            "recordType": "RECORD_TYPE_TRANSFER",
            "recordDate": "2023-09-23",
            "recordUid": "85604"
        },
        {
            "recordDetails": "Transferred and Assigned Infantry C/1/A/2-7",
            "recordType": "RECORD_TYPE_TRANSFER",
            "recordDate": "2023-10-02",
            "recordUid": "86194"
        },
        {
            "recordDetails": "Graduated Boot Camp, Promoted to Private (E-2)",
            "recordType": "RECORD_TYPE_GRADUATION",
            "recordDate": "2023-10-01",
            "recordUid": "86284"
        },
        {
            "recordDetails": "Completed 1st Combat Mission (Campaign 7th Cavalry Expeditionary Force Training Q4 2023. Operation 7th Cavalry Expeditionary Force Training 11OCT23)",
            "recordType": "RECORD_TYPE_OPERATION",
            "recordDate": "2023-10-11",
            "recordUid": "88098"
        },
        {
            "recordDetails": "Promoted to Private First Class (E-3)",
            "recordType": "RECORD_TYPE_PROMOTION",
            "recordDate": "2023-10-31",
            "recordUid": "88972"
        },
        {
            "recordDetails": "Completed 2nd Combat Mission (Operation Buttered Baguette 29OCT23)",
            "recordType": "RECORD_TYPE_OPERATION",
            "recordDate": "2023-10-29",
            "recordUid": "89591"
        },
        {
            "recordDetails": "Completed 3rd Combat Mission (Operation  Archway)",
            "recordType": "RECORD_TYPE_OPERATION",
            "recordDate": "2023-11-04",
            "recordUid": "89961"
        },
        {
            "recordDetails": "Completed 4th Combat Mission (Campaign Let Loose Tuesdays NOV23. Operation Trenched n' Tuesday 07NOV23)",
            "recordType": "RECORD_TYPE_OPERATION",
            "recordDate": "2023-11-07",
            "recordUid": "90122"
        },
        {
            "recordDetails": "Graduated Hell Let Loose Basic Infantry Combat Training Course",
            "recordType": "RECORD_TYPE_GRADUATION",
            "recordDate": "2023-11-27",
            "recordUid": "90551"
        },
        {
            "recordDetails": "Completed 6th Combat Mission (Campaign Let Loose Tuesdays NOV23. Operation Trenched n' Tuesday 21NOV23)",
            "recordType": "RECORD_TYPE_OPERATION",
            "recordDate": "2023-11-21",
            "recordUid": "90680"
        },
        {
            "recordDetails": "Completed 5th Combat Mission (Operation Midnight Falcon 18NOV23)",
            "recordType": "RECORD_TYPE_OPERATION",
            "recordDate": "2023-11-18",
            "recordUid": "91183"
        },
        {
            "recordDetails": "Completed 7th Combat Mission (Campaign Let Loose Tuesdays NOV23. Operation Trenched n' Tuesday 28NOV23)",
            "recordType": "RECORD_TYPE_OPERATION",
            "recordDate": "2023-11-28",
            "recordUid": "91419"
        },
        {
            "recordDetails": "Completed 8th Combat Mission (Campaign Let Loose Tuesdays DEC23. Operation Trenched n' Tuesday 05DEC23)",
            "recordType": "RECORD_TYPE_OPERATION",
            "recordDate": "2023-12-05",
            "recordUid": "91621"
        },
        {
            "recordDetails": "Promoted to Specialist (E-4)",
            "recordType": "RECORD_TYPE_PROMOTION",
            "recordDate": "2023-12-30",
            "recordUid": "92046"
        },
        {
            "recordDetails": "Completed 9th Combat Mission (Operation 2-7 FTX Winter Warriors 16DEC23)",
            "recordType": "RECORD_TYPE_OPERATION",
            "recordDate": "2023-12-16",
            "recordUid": "92452"
        },
        {
            "recordDetails": "Transferred and Assigned Infantry C/2/A/2-7",
            "recordType": "RECORD_TYPE_TRANSFER",
            "recordDate": "2024-01-26",
            "recordUid": "93017"
        },
        {
            "recordDetails": "Completed 10th Combat Mission (Operation Holy Smoke)",
            "recordType": "RECORD_TYPE_OPERATION",
            "recordDate": "2024-02-26",
            "recordUid": "96328"
        },
        {
            "recordDetails": "Completed 11th Combat Mission (Operation Triple Frontier)",
            "recordType": "RECORD_TYPE_OPERATION",
            "recordDate": "2024-04-29",
            "recordUid": "100770"
        },
        {
            "recordDetails": "Assigned Assistant Section Leader C/2/A/2-7",
            "recordType": "RECORD_TYPE_ASSIGNMENT",
            "recordDate": "2024-06-15",
            "recordUid": "104199"
        },
        {
            "recordDetails": "Attended the Server Administration Course",
            "recordType": "RECORD_TYPE_GRADUATION",
            "recordDate": "2024-06-23",
            "recordUid": "105248"
        },
        {
            "recordDetails": "Completed 12th Combat Mission (Operation Luttich)",
            "recordType": "RECORD_TYPE_OPERATION",
            "recordDate": "2024-07-19",
            "recordUid": "107652"
        },
        {
            "recordDetails": "Completed 13th Combat Mission (Operation Scorpion)",
            "recordType": "RECORD_TYPE_OPERATION",
            "recordDate": "2024-08-25",
            "recordUid": "111300"
        },
        {
            "recordDetails": "Completed 14th Combat Mission (Operation Ice House)",
            "recordType": "RECORD_TYPE_OPERATION",
            "recordDate": "2024-09-01",
            "recordUid": "111991"
        },
        {
            "recordDetails": "Completed 15th Combat Mission (Operation Shut Eyes 24h)",
            "recordType": "RECORD_TYPE_OPERATION",
            "recordDate": "2024-09-14",
            "recordUid": "112949"
        },
        {
            "recordDetails": "Graduated NCOA Warrior Leadership Course Phase I",
            "recordType": "RECORD_TYPE_GRADUATION",
            "recordDate": "2024-10-01",
            "recordUid": "114397"
        },
        {
            "recordDetails": "Relieved of Duties as Assistant Section Leader C/2/A/2-7, Assigned Infantry C/2/A/2-7",
            "recordType": "RECORD_TYPE_TRANSFER",
            "recordDate": "2024-10-22",
            "recordUid": "115853"
        },
        {
            "recordDetails": "Completed 16th Combat Mission (Operation The Ridge)",
            "recordType": "RECORD_TYPE_OPERATION",
            "recordDate": "2025-02-24",
            "recordUid": "123793"
        }
    ],
    "awards": [
        {
            "awardDetails": "Awarded for the completion of one or more of the weapons qualification courses with excellent scores.",
            "awardName": "Rifle Expert",
            "awardDate": "2023-10-01",
            "awardImageUrl": "https://7cav.us/data/roster_awards/0/102.jpg?1612850272",
            "awardUid": "46173"
        },
        {
            "awardDetails": "Awarded for the completion of one or more of the weapons qualification courses with excellent scores.",
            "awardName": "Grenade Expert",
            "awardDate": "2023-10-01",
            "awardImageUrl": "https://7cav.us/data/roster_awards/0/105.jpg?1612850347",
            "awardUid": "46177"
        },
        {
            "awardDetails": "",
            "awardName": "Army Service Ribbon",
            "awardDate": "2023-10-01",
            "awardImageUrl": "https://7cav.us/data/roster_awards/0/40.jpg?1612676488",
            "awardUid": "46183"
        },
        {
            "awardDetails": "",
            "awardName": "Army & Air Force Presidential Unit Citation",
            "awardDate": "2003-03-18",
            "awardImageUrl": "https://7cav.us/data/roster_awards/0/61.jpg?1612677152",
            "awardUid": "46189"
        },
        {
            "awardDetails": "",
            "awardName": "Army & Air Force Presidential Unit Citation",
            "awardDate": "2004-09-01",
            "awardImageUrl": "https://7cav.us/data/roster_awards/0/61.jpg?1612677152",
            "awardUid": "46195"
        },
        {
            "awardDetails": "",
            "awardName": "Army & Air Force Presidential Unit Citation",
            "awardDate": "2009-08-10",
            "awardImageUrl": "https://7cav.us/data/roster_awards/0/61.jpg?1612677152",
            "awardUid": "46201"
        },
        {
            "awardDetails": "",
            "awardName": "Army & Air Force Presidential Unit Citation",
            "awardDate": "2010-09-18",
            "awardImageUrl": "https://7cav.us/data/roster_awards/0/61.jpg?1612677152",
            "awardUid": "46207"
        },
        {
            "awardDetails": "",
            "awardName": "Army & Air Force Presidential Unit Citation",
            "awardDate": "2011-06-02",
            "awardImageUrl": "https://7cav.us/data/roster_awards/0/61.jpg?1612677152",
            "awardUid": "46213"
        },
        {
            "awardDetails": "",
            "awardName": "Army & Air Force Presidential Unit Citation",
            "awardDate": "2021-05-16",
            "awardImageUrl": "https://7cav.us/data/roster_awards/0/61.jpg?1612677152",
            "awardUid": "46219"
        },
        {
            "awardDetails": "Awarded for the completion of one or more of the weapons qualification courses with excellent scores.",
            "awardName": "Pistol Expert",
            "awardDate": "2023-10-26",
            "awardImageUrl": "https://7cav.us/data/roster_awards/0/108.jpg?1612850440",
            "awardUid": "47111"
        },
        {
            "awardDetails": "",
            "awardName": "Basic Assault Course Ribbon",
            "awardDate": "2023-11-27",
            "awardImageUrl": "https://7cav.us/data/roster_awards/0/54.jpg?1612676882",
            "awardUid": "48220"
        },
        {
            "awardDetails": "Initial",
            "awardName": "Hell Let Loose Service Ribbon",
            "awardDate": "2023-12-04",
            "awardImageUrl": "https://7cav.us/data/roster_awards/0/47.jpg?1612676643",
            "awardUid": "48567"
        },
        {
            "awardDetails": "",
            "awardName": "Combat Infantry Badge",
            "awardDate": "2023-11-18",
            "awardImageUrl": "https://7cav.us/data/roster_awards/0/68.jpg?1612677377",
            "awardUid": "48938"
        },
        {
            "awardDetails": "Campaign Let Loose Tuesdays NOV23",
            "awardName": "United Nations Service Medal",
            "awardDate": "2023-12-12",
            "awardImageUrl": "https://7cav.us/data/roster_awards/0/42.jpg?1612676525",
            "awardUid": "49340"
        },
        {
            "awardDetails": "",
            "awardName": "Expert Infantry Badge",
            "awardDate": "2023-10-10",
            "awardImageUrl": "https://7cav.us/data/roster_awards/0/67.jpg?1673394869",
            "awardUid": "49598"
        },
        {
            "awardDetails": "Operation Winter Warriors",
            "awardName": "Bronze Star",
            "awardDate": "2024-01-08",
            "awardImageUrl": "https://7cav.us/data/roster_awards/0/12.jpg?1612668131",
            "awardUid": "49659"
        },
        {
            "awardDetails": "",
            "awardName": "Combat Infantry Badge 2nd Award",
            "awardDate": "2024-02-26",
            "awardImageUrl": "https://7cav.us/data/roster_awards/0/69.jpg?1612677441",
            "awardUid": "54249"
        },
        {
            "awardDetails": "S5",
            "awardName": "Outstanding Volunteer Service Medal",
            "awardDate": "2024-06-12",
            "awardImageUrl": "https://7cav.us/data/roster_awards/0/37.jpg?1612676426",
            "awardUid": "57439"
        },
        {
            "awardDetails": "",
            "awardName": "Combat Infantry Badge 3rd Award",
            "awardDate": "2024-09-28",
            "awardImageUrl": "https://7cav.us/data/roster_awards/0/70.jpg?1612677459",
            "awardUid": "62827"
        },
        {
            "awardDetails": "",
            "awardName": "Army Good Conduct Medal",
            "awardDate": "2024-10-01",
            "awardImageUrl": "https://7cav.us/data/roster_awards/0/23.jpg?1612674641",
            "awardUid": "64211"
        },
        {
            "awardDetails": "",
            "awardName": "Soldiers Medal",
            "awardDate": "2024-11-21",
            "awardImageUrl": "https://7cav.us/data/roster_awards/0/10.jpg?1612668084",
            "awardUid": "64578"
        },
        {
            "awardDetails": "1st Award",
            "awardName": "7th Cavalry Black Ops Unit Citation",
            "awardDate": "2025-01-10",
            "awardImageUrl": "https://7cav.us/data/roster_awards/0/66.jpg?1612677259",
            "awardUid": "66263"
        }
    ],
    "joinDate": "2023-09-23",
    "promotionDate": "2023-12-30",
    "keycloakId": "f16b91eb-de43-4302-9a7a-33d0210bf812",
    "discordId": "199312582689947648",
    "lastForumPostDate": "2025-03-13 22:14:49"
}