{
    "user": {
        "userId": "6540",
        "username": "Neubauer.P"
    },
    "rank": {
        "rankShort": "SPC",
        "rankFull": "Specialist",
        "rankImageUrl": "https://7cav.us/data/roster_ranks/0/20.jpg?1741376814",
        "rankId": "20"
    },
    "realName": "Pug Neubauer",
    "uniformUrl": "https://7cav.us/data/roster_uniforms/3/3171.jpg",
    "roster": "ROSTER_TYPE_PAST_MEMBERS",
    "primary": {
        "positionTitle": "Discharged",
        "positionId": "528"
    },
    "secondaries": [],
    "records": [
        {
            "recordDetails": "Enlisted in the 7th Cavalry Regiment, Assigned Boot Camp",
            "recordType": "RECORD_TYPE_TRANSFER",
            "recordDate": "2024-02-23",
            "recordUid": "94780"
        },
        {
            "recordDetails": "Transferred and Assigned Mechanized Infantry D/2/B/1-7",
            "recordType": "RECORD_TYPE_TRANSFER",
            "recordDate": "2024-02-27",
            "recordUid": "95023"
        },
        {
            "recordDetails": "Graduated Boot Camp, Promoted to Private (E-2)",
            "recordType": "RECORD_TYPE_GRADUATION",
            "recordDate": "2024-03-03",
            "recordUid": "95651"
        },
        {
            "recordDetails": "Graduated ARMA3 Basic Land Navigation Course",
            "recordType": "RECORD_TYPE_GRADUATION",
            "recordDate": "2024-03-09",
            "recordUid": "96035"
        },
        {
            "recordDetails": "Completed 1st Combat Mission (Campaign February 2024 Warfare Wednesday. Operation Warfare Wednesday 227)",
            "recordType": "RECORD_TYPE_OPERATION",
            "recordDate": "2024-02-28",
            "recordUid": "96135"
        },
        {
            "recordDetails": "Completed 3rd Combat Mission (Operation Shanty)",
            "recordType": "RECORD_TYPE_OPERATION",
            "recordDate": "2024-03-09",
            "recordUid": "97016"
        },
        {
            "recordDetails": "Graduated ARMA3 Basic Radio Communication Course",
            "recordType": "RECORD_TYPE_GRADUATION",
            "recordDate": "2024-03-18",
            "recordUid": "97041"
        },
        {
            "recordDetails": "Completed 4th Combat Mission (Campaign March 2024 WFW. Operation Warfare Wednesday 229)",
            "recordType": "RECORD_TYPE_OPERATION",
            "recordDate": "2024-03-13",
            "recordUid": "97097"
        },
        {
            "recordDetails": "Graduated ARMA3 Aviation Ground School",
            "recordType": "RECORD_TYPE_GRADUATION",
            "recordDate": "2024-03-20",
            "recordUid": "97150"
        },
        {
            "recordDetails": "Completed 2nd Combat Mission (Campaign March 2024 WFW. Operation Warfare Wednesday 228)",
            "recordType": "RECORD_TYPE_OPERATION",
            "recordDate": "2024-03-06",
            "recordUid": "97222"
        },
        {
            "recordDetails": "Graduated ARMA3 Infantry Heavy Weapons Course",
            "recordType": "RECORD_TYPE_GRADUATION",
            "recordDate": "2024-03-21",
            "recordUid": "97540"
        },
        {
            "recordDetails": "Graduated ARMA3 Basic Infantry Training Course",
            "recordType": "RECORD_TYPE_GRADUATION",
            "recordDate": "2024-03-28",
            "recordUid": "97846"
        },
        {
            "recordDetails": "Graduated ARMA3 Basic Mechanized Infantry Course",
            "recordType": "RECORD_TYPE_GRADUATION",
            "recordDate": "2024-03-29",
            "recordUid": "97941"
        },
        {
            "recordDetails": "Completed 5th Combat Mission (Campaign March 2024 WFW. Operation Warfare Wednesday 230)",
            "recordType": "RECORD_TYPE_OPERATION",
            "recordDate": "2024-03-20",
            "recordUid": "98027"
        },
        {
            "recordDetails": "Completed 6th Combat Mission (Campaign Crisis Response. Operation United Hands)",
            "recordType": "RECORD_TYPE_OPERATION",
            "recordDate": "2024-03-24",
            "recordUid": "98122"
        },
        {
            "recordDetails": "Completed 7th Combat Mission (Campaign March 2024 WFW. Operation Warfare Wednesday 231)",
            "recordType": "RECORD_TYPE_OPERATION",
            "recordDate": "2024-03-27",
            "recordUid": "98647"
        },
        {
            "recordDetails": "Promoted to Private First Class (E-3)",
            "recordType": "RECORD_TYPE_PROMOTION",
            "recordDate": "2024-04-02",
            "recordUid": "98693"
        },
        {
            "recordDetails": "Graduated ARMA3 Basic Airborne Course",
            "recordType": "RECORD_TYPE_GRADUATION",
            "recordDate": "2024-04-09",
            "recordUid": "98792"
        },
        {
            "recordDetails": "Assigned S7 ARMA IS Instructor",
            "recordType": "RECORD_TYPE_ASSIGNMENT",
            "recordDate": "2024-04-10",
            "recordUid": "98888"
        },
        {
            "recordDetails": "Assigned S3 Arma 3 Operations Staff",
            "recordType": "RECORD_TYPE_ASSIGNMENT",
            "recordDate": "2024-04-12",
            "recordUid": "98992"
        },
        {
            "recordDetails": "Completed 9th Combat Mission (Campaign April 2024 WFW. Operation Warfare Wednesday 232)",
            "recordType": "RECORD_TYPE_OPERATION",
            "recordDate": "2024-04-03",
            "recordUid": "99191"
        },
        {
            "recordDetails": "Completed 8th Combat Mission (Operation Amazonian Resolve)",
            "recordType": "RECORD_TYPE_OPERATION",
            "recordDate": "2024-03-30",
            "recordUid": "99243"
        },
        {
            "recordDetails": "Completed 10th Combat Mission (Operation Into The Breach)",
            "recordType": "RECORD_TYPE_OPERATION",
            "recordDate": "2024-04-06",
            "recordUid": "99295"
        },
        {
            "recordDetails": "Completed 11th Combat Mission (Campaign April 2024 WFW. Operation Warfare Wednesday 233)",
            "recordType": "RECORD_TYPE_OPERATION",
            "recordDate": "2024-04-10",
            "recordUid": "99453"
        },
        {
            "recordDetails": "Graduated ARMA3 Door Gunner Course",
            "recordType": "RECORD_TYPE_GRADUATION",
            "recordDate": "2024-04-22",
            "recordUid": "99873"
        },
        {
            "recordDetails": "Completed 12th Combat Mission (Campaign April 2024 WFW. Operation Warfare Wednesday 234)",
            "recordType": "RECORD_TYPE_OPERATION",
            "recordDate": "2024-04-17",
            "recordUid": "100046"
        },
        {
            "recordDetails": "Graduated ARMA3 Basic Air Assault Course",
            "recordType": "RECORD_TYPE_GRADUATION",
            "recordDate": "2024-04-23",
            "recordUid": "100061"
        },
        {
            "recordDetails": "Graduated ARMA3 Aviation Basic Rotary Flight Course",
            "recordType": "RECORD_TYPE_GRADUATION",
            "recordDate": "2024-04-27",
            "recordUid": "100250"
        },
        {
            "recordDetails": "Completed 13th Combat Mission (Operation Swift Freedom)",
            "recordType": "RECORD_TYPE_OPERATION",
            "recordDate": "2024-04-21",
            "recordUid": "100446"
        },
        {
            "recordDetails": "Completed 14th Combat Mission (Campaign April 2024 WFW. Operation Warfare Wednesday 235)",
            "recordType": "RECORD_TYPE_OPERATION",
            "recordDate": "2024-04-24",
            "recordUid": "100681"
        },
        {
            "recordDetails": "Graduated ARMA3 Crew Chief Course",
            "recordType": "RECORD_TYPE_GRADUATION",
            "recordDate": "2024-05-02",
            "recordUid": "100839"
        },
        {
            "recordDetails": "Completed 15th Combat Mission (Operation Trail Blazer)",
            "recordType": "RECORD_TYPE_OPERATION",
            "recordDate": "2024-04-27",
            "recordUid": "101053"
        },
        {
            "recordDetails": "Transferred and Assigned Assistant Section Leader A/2/B/1-7",
            "recordType": "RECORD_TYPE_TRANSFER",
            "recordDate": "2024-05-10",
            "recordUid": "101204"
        },
        {
            "recordDetails": "Completed 16th Combat Mission (Campaign May 2024 WFW. Operation Warfare Wednesday 236)",
            "recordType": "RECORD_TYPE_OPERATION",
            "recordDate": "2024-05-01",
            "recordUid": "101273"
        },
        {
            "recordDetails": "Attended the Server Administration Course",
            "recordType": "RECORD_TYPE_GRADUATION",
            "recordDate": "2024-05-18",
            "recordUid": "101841"
        },
        {
            "recordDetails": "Completed 17th Combat Mission (Campaign Black Bear 24. Operation South Paw)",
            "recordType": "RECORD_TYPE_OPERATION",
            "recordDate": "2024-05-04",
            "recordUid": "101974"
        },
        {
            "recordDetails": "Graduated NCOA Warrior Leadership Course Phase I",
            "recordType": "RECORD_TYPE_GRADUATION",
            "recordDate": "2024-05-25",
            "recordUid": "102392"
        },
        {
            "recordDetails": "Completed 19th Combat Mission (Campaign May 2024 WFW. Operation Warfare Wednesday 239)",
            "recordType": "RECORD_TYPE_OPERATION",
            "recordDate": "2024-05-22",
            "recordUid": "102949"
        },
        {
            "recordDetails": "Completed 18th Combat Mission (Campaign May 2024 WFW. Operation Warfare Wednesday 238)",
            "recordType": "RECORD_TYPE_OPERATION",
            "recordDate": "2024-05-15",
            "recordUid": "103003"
        },
        {
            "recordDetails": "Completed 20th Combat Mission (Operation Bravo Troop FTX Iron Resolve)",
            "recordType": "RECORD_TYPE_OPERATION",
            "recordDate": "2024-05-27",
            "recordUid": "103098"
        },
        {
            "recordDetails": "Graduated NCOA Warrior Leadership Course Phase II",
            "recordType": "RECORD_TYPE_GRADUATION",
            "recordDate": "2024-05-25",
            "recordUid": "103124"
        },
        {
            "recordDetails": "Assigned Section Leader A/2/B/1-7",
            "recordType": "RECORD_TYPE_TRANSFER",
            "recordDate": "2024-06-04",
            "recordUid": "103233"
        },
        {
            "recordDetails": "Completed 21st Combat Mission (Campaign May 2024 WFW. Operation Warfare Wednesday 240)",
            "recordType": "RECORD_TYPE_OPERATION",
            "recordDate": "2024-05-29",
            "recordUid": "103377"
        },
        {
            "recordDetails": "Promoted to Specialist (E-4)",
            "recordType": "RECORD_TYPE_PROMOTION",
            "recordDate": "2024-06-01",
            "recordUid": "103560"
        },
        {
            "recordDetails": "Completed 22nd Combat Mission (Campaign Dynamo. Operation Indigo Tiger)",
            "recordType": "RECORD_TYPE_OPERATION",
            "recordDate": "2024-06-02",
            "recordUid": "103650"
        },
        {
            "recordDetails": "Completed 23rd Combat Mission (Operation Operation Neptune D-1)",
            "recordType": "RECORD_TYPE_OPERATION",
            "recordDate": "2024-06-08",
            "recordUid": "104366"
        },
        {
            "recordDetails": "Completed 24th Combat Mission (Operation Neptune D-Day) Completed 1st Combat Jump",
            "recordType": "RECORD_TYPE_OPERATION",
            "recordDate": "2024-06-08",
            "recordUid": "104500"
        },
        {
            "recordDetails": "Non-punitively relieved of duties as S3 Arma Operations Staff",
            "recordType": "RECORD_TYPE_ASSIGNMENT",
            "recordDate": "2024-07-19",
            "recordUid": "107145"
        },
        {
            "recordDetails": "Honorable Discharge",
            "recordType": "RECORD_TYPE_DISCHARGE",
            "recordDate": "2024-07-26",
            "recordUid": "107725"
        }
    ],
    "awards": [
        {
            "awardDetails": "",
            "awardName": "Army Service Ribbon",
            "awardDate": "2024-03-03",
            "awardImageUrl": "https://7cav.us/data/roster_awards/0/40.jpg?1612676488",
            "awardUid": "51530"
        },
        {
            "awardDetails": "Awarded for the completion of one or more of the weapons qualification courses with above average scores.",
            "awardName": "Rifle Sharpshooter",
            "awardDate": "2024-03-03",
            "awardImageUrl": "https://7cav.us/data/roster_awards/0/101.jpg?1612850250",
            "awardUid": "51796"
        },
        {
            "awardDetails": "Awarded for the completion of one or more of the weapons qualification courses with excellent scores.",
            "awardName": "Grenade Expert",
            "awardDate": "2024-03-03",
            "awardImageUrl": "https://7cav.us/data/roster_awards/0/105.jpg?1612850347",
            "awardUid": "51797"
        },
        {
            "awardDetails": "",
            "awardName": "Army & Air Force Presidential Unit Citation",
            "awardDate": "2003-03-18",
            "awardImageUrl": "https://7cav.us/data/roster_awards/0/61.jpg?1612677152",
            "awardUid": "51842"
        },
        {
            "awardDetails": "",
            "awardName": "Army & Air Force Presidential Unit Citation",
            "awardDate": "2004-09-01",
            "awardImageUrl": "https://7cav.us/data/roster_awards/0/61.jpg?1612677152",
            "awardUid": "51863"
        },
        {
            "awardDetails": "",
            "awardName": "Army & Air Force Presidential Unit Citation",
            "awardDate": "2009-08-10",
            "awardImageUrl": "https://7cav.us/data/roster_awards/0/61.jpg?1612677152",
            "awardUid": "51884"
        },
        {
            "awardDetails": "",
            "awardName": "Army & Air Force Presidential Unit Citation",
            "awardDate": "2010-09-18",
            "awardImageUrl": "https://7cav.us/data/roster_awards/0/61.jpg?1612677152",
            "awardUid": "51904"
        },
        {
            "awardDetails": "",
            "awardName": "Army & Air Force Presidential Unit Citation",
            "awardDate": "2011-06-02",
            "awardImageUrl": "https://7cav.us/data/roster_awards/0/61.jpg?1612677152",
            "awardUid": "51926"
        },
        {
            "awardDetails": "",
            "awardName": "Army & Air Force Presidential Unit Citation",
            "awardDate": "2021-05-16",
            "awardImageUrl": "https://7cav.us/data/roster_awards/0/61.jpg?1612677152",
            "awardUid": "51947"
        },
        {
            "awardDetails": "Operation Warfare Wednesday 227",
            "awardName": "Bronze Star",
            "awardDate": "2024-03-05",
            "awardImageUrl": "https://7cav.us/data/roster_awards/0/12.jpg?1612668131",
            "awardUid": "51984"
        },
        {
            "awardDetails": "Operation Warfare Wednesday 227",
            "awardName": "Army Meritorious Unit Citation",
            "awardDate": "2024-03-08",
            "awardImageUrl": "https://7cav.us/data/roster_awards/0/64.jpg?1612677213",
            "awardUid": "52283"
        },
        {
            "awardDetails": "",
            "awardName": "Expert Infantry Badge",
            "awardDate": "2024-02-28",
            "awardImageUrl": "https://7cav.us/data/roster_awards/0/67.jpg?1673394869",
            "awardUid": "52677"
        },
        {
            "awardDetails": "",
            "awardName": "National Defense Service Medal",
            "awardDate": "2024-03-21",
            "awardImageUrl": "https://7cav.us/data/roster_awards/0/30.jpg?1612676247",
            "awardUid": "52682"
        },
        {
            "awardDetails": "",
            "awardName": "Afghanistan Campaign Medal",
            "awardDate": "2024-03-21",
            "awardImageUrl": "https://7cav.us/data/roster_awards/0/29.jpg?1612674896",
            "awardUid": "52683"
        },
        {
            "awardDetails": "",
            "awardName": "Iraq Campaign Medal",
            "awardDate": "2024-03-21",
            "awardImageUrl": "https://7cav.us/data/roster_awards/0/28.jpg?1612674875",
            "awardUid": "52685"
        },
        {
            "awardDetails": "Initial",
            "awardName": "Overseas Service Ribbon",
            "awardDate": "2024-04-02",
            "awardImageUrl": "https://7cav.us/data/roster_awards/0/43.jpg?1713711737",
            "awardUid": "53224"
        },
        {
            "awardDetails": "",
            "awardName": "Combat Infantry Badge",
            "awardDate": "2024-03-21",
            "awardImageUrl": "https://7cav.us/data/roster_awards/0/68.jpg?1612677377",
            "awardUid": "53248"
        },
        {
            "awardDetails": "",
            "awardName": "Army Parachutist Badge",
            "awardDate": "2024-04-10",
            "awardImageUrl": "https://7cav.us/data/roster_awards/0/83.jpg?1612678149",
            "awardUid": "53522"
        },
        {
            "awardDetails": "",
            "awardName": "Combat Infantry Badge 2nd Award",
            "awardDate": "2024-04-06",
            "awardImageUrl": "https://7cav.us/data/roster_awards/0/69.jpg?1612677441",
            "awardUid": "54345"
        },
        {
            "awardDetails": "",
            "awardName": "Air Assault Badge",
            "awardDate": "2024-04-25",
            "awardImageUrl": "https://7cav.us/data/roster_awards/0/86.jpg?1612678230",
            "awardUid": "54437"
        },
        {
            "awardDetails": "Awarded for the completion of one or more of the weapons qualification courses with average scores.",
            "awardName": "Aeroweapons Marksman",
            "awardDate": "2024-04-22",
            "awardImageUrl": "https://7cav.us/data/roster_awards/0/109.jpg?1612850470",
            "awardUid": "54472"
        },
        {
            "awardDetails": "1st Award",
            "awardName": "Humanitarian Service Medal",
            "awardDate": "2024-04-29",
            "awardImageUrl": "https://7cav.us/data/roster_awards/0/33.jpg?1612676322",
            "awardUid": "54802"
        },
        {
            "awardDetails": "",
            "awardName": "Soldiers Medal",
            "awardDate": "2024-05-02",
            "awardImageUrl": "https://7cav.us/data/roster_awards/0/10.jpg?1612668084",
            "awardUid": "55076"
        },
        {
            "awardDetails": "",
            "awardName": "Meritorious Service Medal",
            "awardDate": "2024-05-02",
            "awardImageUrl": "https://7cav.us/data/roster_awards/0/15.jpg?1612668368",
            "awardUid": "55084"
        },
        {
            "awardDetails": "",
            "awardName": "Aircraft Crewman Badge",
            "awardDate": "2024-05-02",
            "awardImageUrl": "https://7cav.us/data/roster_awards/0/80.jpg?1614217877",
            "awardUid": "55250"
        },
        {
            "awardDetails": "",
            "awardName": "Combat Infantry Badge 3rd Award",
            "awardDate": "2024-04-27",
            "awardImageUrl": "https://7cav.us/data/roster_awards/0/70.jpg?1612677459",
            "awardUid": "55836"
        },
        {
            "awardDetails": "",
            "awardName": "Combat Infantry Badge 3rd Award",
            "awardDate": "2024-04-28",
            "awardImageUrl": "https://7cav.us/data/roster_awards/0/70.jpg?1612677459",
            "awardUid": "55923"
        },
        {
            "awardDetails": "MAR24",
            "awardName": "United Nations Service Medal",
            "awardDate": "2024-03-27",
            "awardImageUrl": "https://7cav.us/data/roster_awards/0/42.jpg?1612676525",
            "awardUid": "56237"
        },
        {
            "awardDetails": "Warfare Wednesday APR24",
            "awardName": "United Nations Service Medal",
            "awardDate": "2024-04-24",
            "awardImageUrl": "https://7cav.us/data/roster_awards/0/42.jpg?1612676525",
            "awardUid": "56281"
        },
        {
            "awardDetails": "Operation Iron Resolve",
            "awardName": "Bronze Star with Valor Device",
            "awardDate": "2024-06-03",
            "awardImageUrl": "https://7cav.us/data/roster_awards/0/11.jpg?1612668108",
            "awardUid": "56454"
        },
        {
            "awardDetails": "Campaign Warfare Wednesday MAY24",
            "awardName": "United Nations Service Medal",
            "awardDate": "2024-05-29",
            "awardImageUrl": "https://7cav.us/data/roster_awards/0/42.jpg?1612676525",
            "awardUid": "57271"
        },
        {
            "awardDetails": "",
            "awardName": "D-Day Commemorative Medal",
            "awardDate": "2024-06-11",
            "awardImageUrl": "https://7cav.us/data/roster_awards/0/50.jpg?1612676791",
            "awardUid": "57464"
        },
        {
            "awardDetails": "",
            "awardName": "Combat Infantry Badge 4th Award",
            "awardDate": "2024-05-26",
            "awardImageUrl": "https://7cav.us/data/roster_awards/0/71.jpg?1612677477",
            "awardUid": "57609"
        },
        {
            "awardDetails": "",
            "awardName": "Global War on Terrorism Expeditionary Medal",
            "awardDate": "2024-03-11",
            "awardImageUrl": "https://7cav.us/data/roster_awards/0/31.jpg?1612676268",
            "awardUid": "57659"
        },
        {
            "awardDetails": "1st Award",
            "awardName": "Donation Ribbon",
            "awardDate": "2024-03-31",
            "awardImageUrl": "https://7cav.us/data/roster_awards/0/34.jpg?1612676352",
            "awardUid": "60595"
        },
        {
            "awardDetails": "2nd Award",
            "awardName": "Donation Ribbon",
            "awardDate": "2024-04-30",
            "awardImageUrl": "https://7cav.us/data/roster_awards/0/34.jpg?1612676352",
            "awardUid": "60703"
        }
    ],
    "joinDate": "2024-02-23",
    "promotionDate": "2024-06-01",
    "keycloakId": "2fe6179e-9783-4e02-8e9f-fe061c08661c",
    "discordId": "658851164485320722",
    "lastForumPostDate": "2024-06-29 05:08:55"
}